[
  {
    "question": "Which sentence correctly uses the simple present tense to state a fact?",
    "correct": "Monsoons occur in India.",
    "options": [
      "Monsoons is occurring in India.",
      "Monsoons occur in India.",
      "Monsoons has occurred in India.",
      "Monsoons were occurring in India."
    ],
    "difficulty": "easy",
    "questionType": "mcq",
    "topic": "Simple Present Tense",
    "complexity_score": 1
  },
  {
    "question": "Choose the correct verb form for the sentence: 'Ankitah ______ already completed her exam.'",
    "correct": "has",
    "options": [
      "is",
      "has",
      "have",
      "was"
    ],
    "difficulty": "easy",
    "questionType": "mcq",
    "topic": "Present Perfect Tense",
    "complexity_score": 1
  },
  {
    "question": "Which sentence correctly uses the present continuous tense?",
    "correct": "She is making a life-size painting.",
    "options": [
      "She makes a life-size painting now.",
      "She has been make a life-size painting.",
      "She is making a life-size painting.",
      "She made a life-size painting."
    ],
    "difficulty": "easy",
    "questionType": "mcq",
    "topic": "Present Continuous Tense",
    "complexity_score": 1
  },
  {
    "question": "In the jungle safari story, what were the deer doing?",
    "correct": "Grazing on leaves",
    "options": [
      "Driving a jeep",
      "Roaring loudly",
      "Grazing on leaves",
      "Spotting a tiger"
    ],
    "difficulty": "easy",
    "questionType": "mcq",
    "topic": "Vocabulary in Context",
    "complexity_score": 1
  },
  {
    "question": "Choose the correct sentence: 'What ______ you reading?'",
    "correct": "are",
    "options": [
      "is",
      "do",
      "are",
      "has"
    ],
    "difficulty": "easy",
    "questionType": "mcq",
    "topic": "Subject-Verb Agreement",
    "complexity_score": 1
  },
  {
    "question": "Which verb form correctly completes the sentence: 'Mohan has ______ for several jobs.'?",
    "correct": "applied",
    "options": [
      "apply",
      "applies",
      "applying",
      "applied"
    ],
    "difficulty": "easy",
    "questionType": "mcq",
    "topic": "Present Perfect Tense",
    "complexity_score": 1
  },
  {
    "question": "The phrase 'since yesterday' is a clue to use which tense?",
    "correct": "Present Perfect Continuous",
    "options": [
      "Simple Present",
      "Present Continuous",
      "Simple Past",
      "Present Perfect Continuous"
    ],
    "difficulty": "medium",
    "questionType": "mcq",
    "topic": "Tense Identification",
    "complexity_score": 2
  },
  {
    "question": "Change the sentence to Present Perfect Tense: 'He was questioned by his father.'",
    "correct": "He has been questioned by his father.",
    "options": [
      "He is questioning his father.",
      "He has been questioned by his father.",
      "He was being questioned by his father.",
      "He has questioned his father."
    ],
    "difficulty": "medium",
    "questionType": "mcq",
    "topic": "Tense Transformation",
    "complexity_score": 2
  },
  {
    "question": "Which sentence correctly fixes the error: 'She and his friends is practicing judo.'?",
    "correct": "She and her friends are practicing judo.",
    "options": [
      "She and his friends was practicing judo.",
      "She and her friends are practicing judo.",
      "She and his friends has been practicing judo.",
      "She and her friends is practicing judo."
    ],
    "difficulty": "medium",
    "questionType": "mcq",
    "topic": "Subject-Verb Agreement",
    "complexity_score": 2
  },
  {
    "question": "Why is 'have been playing' the correct choice for: 'The children are tired because they ______ in the field all morning.'?",
    "correct": "The action happened over a period of time ('all morning').",
    "options": [
      "The children are plural.",
      "The action is happening right now.",
      "The action happened over a period of time ('all morning').",
      "The sentence is in the past tense."
    ],
    "difficulty": "medium",
    "questionType": "mcq",
    "topic": "Tense Rationale",
    "complexity_score": 3
  },
  {
    "question": "Complete the sentence: 'We ______ to find our way home for the last two hours.'",
    "correct": "have been trying",
    "options": [
      "are trying",
      "have been trying",
      "try",
      "had tried"
    ],
    "difficulty": "medium",
    "questionType": "mcq",
    "topic": "Present Perfect Continuous",
    "complexity_score": 2
  },
  {
    "question": "Which sentence correctly fixes the error: 'What game is those children playing?'?",
    "correct": "What game are those children playing?",
    "options": [
      "What game was those children playing?",
      "What game are those children playing?",
      "What game has those children playing?",
      "What game do those children play?"
    ],
    "difficulty": "medium",
    "questionType": "mcq",
    "topic": "Error Correction",
    "complexity_score": 2
  },
  {
    "question": "The verb 'roam' means to wander or travel without a specific destination. Which sentence uses it correctly?",
    "correct": "Wild animals roam freely through the national park.",
    "options": [
      "Please roam the book on the table.",
      "Wild animals roam freely through the national park.",
      "He roam his voice in anger.",
      "The car will roam to a stop."
    ],
    "difficulty": "medium",
    "questionType": "mcq",
    "topic": "Vocabulary Application",
    "complexity_score": 2
  },
  {
    "question": "Fill in the blank: 'He ______ the car for three hours now.'",
    "correct": "has been washing",
    "options": [
      "is washing",
      "washes",
      "has been washing",
      "washed"
    ],
    "difficulty": "medium",
    "questionType": "mcq",
    "topic": "Present Perfect Continuous",
    "complexity_score": 2
  },
  {
    "question": "The Public Health Department is a single entity. Which verb form is correct: 'The department ______ putting stress on sanitation.'?",
    "correct": "has been",
    "options": [
      "have been",
      "are",
      "has been",
      "were"
    ],
    "difficulty": "hard",
    "questionType": "mcq",
    "topic": "Collective Nouns",
    "complexity_score": 4
  },
  {
    "question": "Analyze this sentence: 'The people who ______ to the office by foot now should take the bus.' Why is 'walk' (simple present) or 'are walking' (present continuous) better than 'have been walking'?",
    "correct": "It describes a habitual action or a current state, not an action over a specific duration.",
    "options": [
      "Because 'people' is plural.",
      "It describes a habitual action or a current state, not an action over a specific duration.",
      "The sentence has the word 'now' in it.",
      "Because the action is already finished."
    ],
    "difficulty": "hard",
    "questionType": "mcq",
    "topic": "Tense Nuances",
    "complexity_score": 5
  },
  {
    "question": "Your daughter ______ you the same thing since you got here.' Which is the correct verb form and why?",
    "correct": "'has been telling', because 'since' indicates a continuous action from a past point until now.",
    "options": [
      "'is telling', because the action is happening now.",
      "'told', because the action is in the past.",
      "'has been telling', because 'since' indicates a continuous action from a past point until now.",
      "'tells', because it is a habit."
    ],
    "difficulty": "hard",
    "questionType": "mcq",
    "topic": "Tense Analysis",
    "complexity_score": 4
  },
  {
    "question": "Consider the sentence: 'How is he doing after the accident?' What does this question imply?",
    "correct": "It asks about his current state of recovery or well-being.",
    "options": [
      "It asks what actions he performed during the accident.",
      "It asks if he is currently causing another accident.",
      "It asks about his current state of recovery or well-being.",
      "It asks for a description of the accident itself."
    ],
    "difficulty": "hard",
    "questionType": "mcq",
    "topic": "Inferential Comprehension",
    "complexity_score": 4
  },
  {
    "question": "In the student's story, 'Then suddenly a tiger arive and dragging the deer.' How could this be improved for better narrative flow in the present tense?",
    "correct": "Then suddenly a tiger arrives and starts dragging the deer.",
    "options": [
      "Then suddenly a tiger was arriving and dragged the deer.",
      "Then suddenly a tiger has arrived and is dragging the deer.",
      "Then suddenly a tiger arrive and drag the deer.",
      "Then suddenly a tiger arrives and starts dragging the deer."
    ],
    "difficulty": "hard",
    "questionType": "mcq",
    "topic": "Creative Writing & Tense",
    "complexity_score": 5
  },
  {
    "question": "Which of these situations would NOT use the Present Perfect Continuous tense ('has/have been -ing')?",
    "correct": "Describing a single, completed action in the past.",
    "options": [
      "Talking about an action that started in the past and is still going on.",
      "Explaining the cause of a present result (e.g., 'I'm tired because I've been running').",
      "Describing a single, completed action in the past.",
      "Emphasizing the duration of an action ('She has been studying for three hours')."
    ],
    "difficulty": "hard",
    "questionType": "mcq",
    "topic": "Tense Application Theory",
    "complexity_score": 5
  }
]