[
  {
    "question": "Which sentence correctly uses the simple present tense for a habitual action?",
    "correct": "I watch the bird make its nest every morning.",
    "options": [
      "I am watching the bird make its nest every morning.",
      "I have watched the bird make its nest every morning.",
      "I watch the bird make its nest every morning.",
      "I was watching the bird make its nest every morning."
    ],
    "difficulty": "easy",
    "questionType": "mcq",
    "topic": "Simple Present Tense",
    "complexity_score": 1
  },
  {
    "question": "In the sentence 'Ankitah has already _______ her class 12 exams,' which is the correct form of the verb 'complete'?",
    "correct": "completed",
    "options": [
      "completing",
      "complete",
      "completes",
      "completed"
    ],
    "difficulty": "easy",
    "questionType": "mcq",
    "topic": "Present Perfect Tense",
    "complexity_score": 1
  },
  {
    "question": "Choose the correct verb for the sentence: 'She and his friends ____ practicing judo.'",
    "correct": "are",
    "options": [
      "is",
      "are",
      "was",
      "be"
    ],
    "difficulty": "easy",
    "questionType": "mcq",
    "topic": "Subject-Verb Agreement",
    "complexity_score": 1
  },
  {
    "question": "Which question is grammatically correct?",
    "correct": "What game are those children playing?",
    "options": [
      "What game is those children playing?",
      "What game are those children playing?",
      "What game those children are playing?",
      "What game does those children play?"
    ],
    "difficulty": "easy",
    "questionType": "mcq",
    "topic": "Subject-Verb Agreement",
    "complexity_score": 1
  },
  {
    "question": "Complete the sentence: 'I ____ not working at present.'",
    "correct": "am",
    "options": [
      "is",
      "are",
      "have",
      "am"
    ],
    "difficulty": "easy",
    "questionType": "mcq",
    "topic": "Present Continuous Tense",
    "complexity_score": 1
  },
  {
    "question": "The verb 'graze' means to:",
    "correct": "Eat grass in a field",
    "options": [
      "Run quickly",
      "Look at something with surprise",
      "Eat grass in a field",
      "Build a nest"
    ],
    "difficulty": "easy",
    "questionType": "mcq",
    "topic": "Vocabulary",
    "complexity_score": 1
  },
  {
    "question": "Which sentence correctly uses the Present Perfect Continuous tense?",
    "correct": "He has been driving the car for three hours.",
    "options": [
      "He is driving the car for three hours.",
      "He drives the car for three hours.",
      "He has been driving the car for three hours.",
      "He has driven the car for three hours."
    ],
    "difficulty": "medium",
    "questionType": "mcq",
    "topic": "Present Perfect Continuous Tense",
    "complexity_score": 2
  },
  {
    "question": "Identify the error: 'Moha has apply for several jobs.'",
    "correct": "The verb 'apply' should be 'applied'.",
    "options": [
      "The subject 'Moha' is incorrect.",
      "The verb 'apply' should be 'applied'.",
      "The helping verb 'has' should be 'is'.",
      "There is no error in the sentence."
    ],
    "difficulty": "medium",
    "questionType": "mcq",
    "topic": "Present Perfect Tense",
    "complexity_score": 2
  },
  {
    "question": "The word 'since' is a clue that we should probably use which tense?",
    "correct": "Present Perfect Continuous",
    "options": [
      "Simple Present",
      "Present Continuous",
      "Present Perfect Continuous",
      "Simple Past"
    ],
    "difficulty": "medium",
    "questionType": "mcq",
    "topic": "Tense Identification",
    "complexity_score": 2
  },
  {
    "question": "Choose the correct sentence: 'The Public Health Department ____ putting a lot of stress on sanitation.' (Department is a single entity).",
    "correct": "has been",
    "options": [
      "have been",
      "are",
      "is being",
      "has been"
    ],
    "difficulty": "medium",
    "questionType": "mcq",
    "topic": "Subject-Verb Agreement",
    "complexity_score": 2
  },
  {
    "question": "In the story, if a tiger 'arrives' and 'starts dragging' a deer, what tense is being used to create a sense of immediate action?",
    "correct": "Simple Present",
    "options": [
      "Simple Past",
      "Present Continuous",
      "Simple Present",
      "Present Perfect"
    ],
    "difficulty": "medium",
    "questionType": "mcq",
    "topic": "Literary Tense Use",
    "complexity_score": 3
  },
  {
    "question": "Change the sentence to Present Perfect tense: 'He was questioned by his father.'",
    "correct": "He has been questioned by his father.",
    "options": [
      "He has questioned his father.",
      "He is being questioned by his father.",
      "He has been questioned by his father.",
      "He is questioning his father."
    ],
    "difficulty": "medium",
    "questionType": "mcq",
    "topic": "Tense Transformation",
    "complexity_score": 3
  },
  {
    "question": "The children are tired because they ______ in the field all morning.",
    "correct": "have been playing",
    "options": [
      "are playing",
      "play",
      "have been playing",
      "did play"
    ],
    "difficulty": "medium",
    "questionType": "mcq",
    "topic": "Present Perfect Continuous Tense",
    "complexity_score": 2
  },
  {
    "question": "Which verb from the list (see, arrive, drive, tell, spot, roam) best fits the blank? 'I looked across the savannah and managed to ____ a lion hiding in the grass.'",
    "correct": "spot",
    "options": [
      "roam",
      "drive",
      "spot",
      "tell"
    ],
    "difficulty": "medium",
    "questionType": "mcq",
    "topic": "Vocabulary in Context",
    "complexity_score": 2
  },
  {
    "question": "Why is 'It has been snowing continuously since yesterday' correct, while 'It is snowing continuously since yesterday' is incorrect?",
    "correct": "Because 'since yesterday' indicates an action that started in the past and continues to the present.",
    "options": [
      "Because 'snowing' is a past tense verb.",
      "Because 'is' cannot be used with 'continuously'.",
      "Because 'since yesterday' indicates an action that started in thepast and continues to the present.",
      "Because 'has been' sounds more formal."
    ],
    "difficulty": "hard",
    "questionType": "mcq",
    "topic": "Tense Analysis",
    "complexity_score": 4
  },
  {
    "question": "In the sentence 'She is seeing him on Sunday,' the present continuous tense is used to talk about...",
    "correct": "A future plan or arrangement.",
    "options": [
      "An action happening right now.",
      "A scientific fact.",
      "A past event.",
      "A future plan or arrangement."
    ],
    "difficulty": "hard",
    "questionType": "mcq",
    "topic": "Advanced Tense Application",
    "complexity_score": 4
  },
  {
    "question": "Consider the sentence: 'The people who ____ to the office by foot now should take the bus.' Why is 'are walking' or 'walk' a better choice than 'have been walking'?",
    "correct": "Because the sentence describes a general habit, not an action with a specific duration.",
    "options": [
      "Because 'people' is singular.",
      "Because 'now' always signals the simple present tense.",
      "Because the sentence describes a general habit, not an action with a specific duration.",
      "Because 'take the bus' is in the past tense."
    ],
    "difficulty": "hard",
    "questionType": "mcq",
    "topic": "Tense Nuance",
    "complexity_score": 5
  },
  {
    "question": "How does the meaning change between 'How is he doing after the accident?' and 'What is he doing after the accident?'",
    "correct": "'How is he doing?' asks about his well-being, while 'What is he doing?' asks about his actions.",
    "options": [
      "There is no change in meaning.",
      "'How is he doing?' asks about his location, while 'What is he doing?' asks about his feelings.",
      "'How is he doing?' asks about his well-being, while 'What is he doing?' asks about his actions.",
      "'How is he doing?' is grammatically incorrect."
    ],
    "difficulty": "hard",
    "questionType": "mcq",
    "topic": "Semantic Analysis",
    "complexity_score": 4
  },
  {
    "question": "To write a story about an experience like a jungle safari, a writer might start in the past tense ('I arrived') but switch to the present tense ('a tiger appears!') to...",
    "correct": "Create a sense of immediacy and excitement for the reader.",
    "options": [
      "Show that they forgot which tense to use.",
      "Follow a strict grammar rule for stories.",
      "Create a sense of immediacy and excitement for the reader.",
      "Indicate that the story is not true."
    ],
    "difficulty": "hard",
    "questionType": "mcq",
    "topic": "Literary Devices",
    "complexity_score": 5
  },
  {
    "question": "Your daughter ____ you the same thing since you got here.' Which option is correct and why?",
    "correct": "'has been telling' because of the time indicator 'since you got here'.",
    "options": [
      "'is telling' because the action is happening now.",
      "'tells' because it is a repeated action.",
      "'has been telling' because of the time indicator 'since you got here'.",
      "'was telling' because the action started in the past."
    ],
    "difficulty": "hard",
    "questionType": "mcq",
    "topic": "Tense Analysis",
    "complexity_score": 4
  }
]